verysimplemodule/__init__.py
verysimplemodule/divide.py
verysimplemodule/multiply.py
verysimplemodule/extras/__init__.py
verysimplemodule/extras/add.py
verysimplemodule/extras/subtract.py
verysimplemoduleuluk/__init__.py
verysimplemoduleuluk/divide.py
verysimplemoduleuluk/multiply.py
verysimplemoduleuluk/extras/__init__.py
verysimplemoduleuluk/extras/add.py
verysimplemoduleuluk/extras/subtract.py
verysimplemoduleuluk-0.0.1.dist-info/METADATA
verysimplemoduleuluk-0.0.1.dist-info/WHEEL
verysimplemoduleuluk-0.0.1.dist-info/top_level.txt
verysimplemoduleuluk-0.0.1.dist-info/RECORD
